lambda_tools/__init__.py
lambda_tools/build.py
lambda_tools/command.py
lambda_tools/configuration.py
lambda_tools/deploy.py
lambda_tools/mapper.py
lambda_tools/test_runners.py
airsupply_lambda_tools-0.2.0a4.dist-info/LICENSE.txt
airsupply_lambda_tools-0.2.0a4.dist-info/METADATA
airsupply_lambda_tools-0.2.0a4.dist-info/WHEEL
airsupply_lambda_tools-0.2.0a4.dist-info/entry_points.txt
airsupply_lambda_tools-0.2.0a4.dist-info/top_level.txt
airsupply_lambda_tools-0.2.0a4.dist-info/RECORD
